jijmodeling_transpiler_quantum/qiskit/__init__.py
jijmodeling_transpiler_quantum/qiskit/qaoa/__init__.py
jijmodeling_transpiler_quantum/qiskit/qaoa/ising_hamiltonian.py
jijmodeling_transpiler_quantum/qiskit/qaoa/to_qaoa.py
jijmodeling_transpiler_quantum/qiskit/qrao/__init__.py
jijmodeling_transpiler_quantum/qiskit/qrao/qrao21.py
jijmodeling_transpiler_quantum/qiskit/qrao/qrao31.py
jijmodeling_transpiler_quantum/qiskit/qrao/to_qrac.py
jijmodeling_transpiler_quantum_qiskit-0.1.0rc2.dist-info/METADATA
jijmodeling_transpiler_quantum_qiskit-0.1.0rc2.dist-info/WHEEL
jijmodeling_transpiler_quantum_qiskit-0.1.0rc2.dist-info/RECORD
