Metadata-Version: 2.1
Name: jijmodeling-transpiler-quantum-qiskit
Version: 0.1.0rc2
Summary: JijModeling Transpiler for Qiskit
Author: Jij Inc.
Requires-Python: >=3.9,<3.11
Classifier: Programming Language :: Python :: 3
Classifier: Programming Language :: Python :: 3.9
Classifier: Programming Language :: Python :: 3.10
Requires-Dist: jijmodeling-transpiler-quantum
Requires-Dist: qiskit (>=0.43.1)
